xbox/auxiliary/__init__.py
xbox/auxiliary/crypto.py
xbox/auxiliary/manager.py
xbox/auxiliary/packer.py
xbox/auxiliary/packet.py
xbox/auxiliary/relay.py
xbox/handlers/__init__.py
xbox/handlers/fallout4_relay.py
xbox/handlers/gamepad_input.py
xbox/handlers/text_input.py
xbox/handlers/tui.py
xbox/rest/__init__.py
xbox/rest/api.py
xbox/rest/app.py
xbox/rest/common.py
xbox/rest/consolewrap.py
xbox/rest/deps.py
xbox/rest/singletons.py
xbox/rest/routes/__init__.py
xbox/rest/routes/auth.py
xbox/rest/routes/device.py
xbox/rest/routes/root.py
xbox/rest/routes/web.py
xbox/rest/schemas/__init__.py
xbox/rest/schemas/auth.py
xbox/rest/schemas/device.py
xbox/rest/schemas/general.py
xbox/rest/schemas/root.py
xbox/scripts/__init__.py
xbox/scripts/main_cli.py
xbox/scripts/pcap.py
xbox/scripts/recrypt.py
xbox/scripts/rest_server.py
xbox/sg/__init__.py
xbox/sg/console.py
xbox/sg/constants.py
xbox/sg/crypto.py
xbox/sg/enum.py
xbox/sg/factory.py
xbox/sg/manager.py
xbox/sg/packer.py
xbox/sg/protocol.py
xbox/sg/packet/__init__.py
xbox/sg/packet/message.py
xbox/sg/packet/simple.py
xbox/sg/utils/__init__.py
xbox/sg/utils/adapters.py
xbox/sg/utils/events.py
xbox/sg/utils/struct.py
xbox/stump/__init__.py
xbox/stump/enum.py
xbox/stump/json_model.py
xbox/stump/manager.py
xbox_smartglass_core-1.3.0.dist-info/LICENSE
xbox_smartglass_core-1.3.0.dist-info/METADATA
xbox_smartglass_core-1.3.0.dist-info/WHEEL
xbox_smartglass_core-1.3.0.dist-info/entry_points.txt
xbox_smartglass_core-1.3.0.dist-info/top_level.txt
xbox_smartglass_core-1.3.0.dist-info/RECORD
