Metadata-Version: 2.1
Name: xbox-smartglass-core
Version: 1.3.0
Summary: A library to interact with the Xbox One gaming console via the SmartGlass protocol.
Home-page: https://github.com/OpenXbox/xbox-smartglass-core-python
Author: OpenXbox
Author-email: noreply@openxbox.org
License: MIT
Keywords: xbox one smartglass auxiliary fallout title stump tv streaming livetv rest api
Platform: UNKNOWN
Classifier: Development Status :: 4 - Beta
Classifier: Intended Audience :: Developers
Classifier: License :: OSI Approved :: MIT License
Classifier: Topic :: Software Development :: Libraries :: Python Modules
Classifier: Programming Language :: Python :: 3
Classifier: Programming Language :: Python :: 3.7
Classifier: Programming Language :: Python :: 3.8
Classifier: Programming Language :: Python :: 3.9
Requires-Python: >=3.7
Requires-Dist: xbox-webapi (==2.0.9)
Requires-Dist: construct (==2.10.56)
Requires-Dist: cryptography (==3.2.1)
Requires-Dist: dpkt (==1.9.4)
Requires-Dist: pydantic (==1.7.1)
Requires-Dist: aioconsole (==0.3.0)
Requires-Dist: fastapi (==0.61.1)
Requires-Dist: uvicorn (==0.12.2)
Requires-Dist: urwid (==2.1.2)
Provides-Extra: dev
Requires-Dist: pip ; extra == 'dev'
Requires-Dist: bump2version ; extra == 'dev'
Requires-Dist: wheel ; extra == 'dev'
Requires-Dist: watchdog ; extra == 'dev'
Requires-Dist: flake8 ; extra == 'dev'
Requires-Dist: coverage ; extra == 'dev'
Requires-Dist: Sphinx ; extra == 'dev'
Requires-Dist: sphinx-rtd-theme ; extra == 'dev'
Requires-Dist: recommonmark ; extra == 'dev'
Requires-Dist: twine ; extra == 'dev'
Requires-Dist: pytest ; extra == 'dev'
Requires-Dist: pytest-asyncio ; extra == 'dev'
Requires-Dist: pytest-console-scripts ; extra == 'dev'
Requires-Dist: pytest-runner ; extra == 'dev'
